README.txt
setup.py
garbas/__init__.py
garbas.watermark.egg-info/PKG-INFO
garbas.watermark.egg-info/SOURCES.txt
garbas.watermark.egg-info/dependency_links.txt
garbas.watermark.egg-info/entry_points.txt
garbas.watermark.egg-info/namespace_packages.txt
garbas.watermark.egg-info/not-zip-safe
garbas.watermark.egg-info/requires.txt
garbas.watermark.egg-info/top_level.txt
garbas/watermark/__init__.py
garbas/watermark/tests.py
garbas/watermark/watermarkfield.py
