Metadata-Version: 1.0
Name: garbas.watermark
Version: 0.1b1
Summary: AT Image field with watermark
Home-page: http://github.com/garbas/garbas.watermark
Author: Rok Garbas
Author-email: rok.garbas@gmail.com
License: GPL
Keywords: plone
Platform: UNKNOWN
Classifier: Framework :: Plone
Classifier: Framework :: Zope2
Classifier: Framework :: Zope3
Classifier: Programming Language :: Python
Classifier: Topic :: Software Development :: Libraries :: Python Modules
